MANIFEST.in
README.md
setup.cfg
setup.py
dgeq/__init__.py
dgeq/aggregations.py
dgeq/censor.py
dgeq/commands.py
dgeq/constants.py
dgeq/dgeq.py
dgeq/exceptions.py
dgeq/filter.py
dgeq/joins.py
dgeq/types.py
dgeq/utils.py
dgeq.egg-info/PKG-INFO
dgeq.egg-info/SOURCES.txt
dgeq.egg-info/dependency_links.txt
dgeq.egg-info/requires.txt
dgeq.egg-info/top_level.txt
docs/CHANGELOG.md